{"__symbolic":"module","version":4,"metadata":{"SettingManagementNgAlainModule":{"__symbolic":"class","decorators":[{"__symbolic":"call","expression":{"__symbolic":"reference","module":"@angular/core","name":"NgModule","line":6,"character":1},"arguments":[{"imports":[{"__symbolic":"reference","module":"@fs/ng-alain/basic","name":"NgAlainBasicModule","line":9,"character":4},{"__symbolic":"reference","name":"ɵa"}],"exports":[]}]}],"members":{}},"ɵa":{"__symbolic":"class","decorators":[{"__symbolic":"call","expression":{"__symbolic":"reference","module":"@angular/core","name":"NgModule","line":18,"character":1},"arguments":[{"imports":[{"__symbolic":"call","expression":{"__symbolic":"select","expression":{"__symbolic":"reference","module":"@angular/router","name":"RouterModule","line":19,"character":12},"member":"forChild"},"arguments":[[{"path":"","pathMatch":"full","redirectTo":"settings"},{"path":"","children":[{"path":"settings"}]}]]}],"exports":[{"__symbolic":"reference","module":"@angular/router","name":"RouterModule","line":20,"character":12}]}]}],"members":{}}},"origins":{"SettingManagementNgAlainModule":"./lib/setting-management-ng-alain.module","ɵa":"./lib/setting-management-ng-alain-routing.module"},"importAs":"@fs/setting-management/ng-alain"}