{"__symbolic":"module","version":4,"exports":[{"from":"./lib/common-utils"},{"from":"./lib/generator-utils"},{"from":"./lib/initial-utils"},{"from":"./lib/route-utils"},{"from":"./lib/rxjs-utils"},{"from":"./lib/profile.service"},{"from":"./lib/rest.service"},{"from":"./lib/profile-state.service"},{"from":"./lib/session-state.service"}],"metadata":{"storageFactory":{"__symbolic":"function","parameters":[],"value":{"__symbolic":"reference","name":"localStorage"}},"CoreModule":{"__symbolic":"class","decorators":[{"__symbolic":"call","expression":{"__symbolic":"reference","module":"@angular/core","name":"NgModule","line":39,"character":1},"arguments":[{"imports":[{"__symbolic":"call","expression":{"__symbolic":"select","expression":{"__symbolic":"reference","module":"@ngxs/store","name":"NgxsModule","line":41,"character":4},"member":"forFeature"},"arguments":[[{"__symbolic":"reference","name":"ɵa"},{"__symbolic":"reference","name":"ɵd"},{"__symbolic":"reference","name":"ɵk"},{"__symbolic":"reference","name":"ɵr"}]]},{"__symbolic":"call","expression":{"__symbolic":"select","expression":{"__symbolic":"reference","module":"@ngxs/router-plugin","name":"NgxsRouterPluginModule","line":42,"character":4},"member":"forRoot"}},{"__symbolic":"call","expression":{"__symbolic":"select","expression":{"__symbolic":"reference","module":"@ngxs/storage-plugin","name":"NgxsStoragePluginModule","line":43,"character":4},"member":"forRoot"},"arguments":[{"key":["SessionState"]}]},{"__symbolic":"reference","module":"angular-oauth2-oidc","name":"OAuthModule","line":44,"character":4},{"__symbolic":"reference","module":"@angular/common","name":"CommonModule","line":45,"character":4},{"__symbolic":"reference","module":"@angular/common/http","name":"HttpClientModule","line":46,"character":4},{"__symbolic":"reference","module":"@angular/forms","name":"FormsModule","line":47,"character":4},{"__symbolic":"reference","module":"@angular/forms","name":"ReactiveFormsModule","line":48,"character":4},{"__symbolic":"reference","module":"@angular/router","name":"RouterModule","line":49,"character":4}],"declarations":[{"__symbolic":"reference","name":"ɵy"},{"__symbolic":"reference","name":"ɵz"},{"__symbolic":"reference","name":"ɵba"},{"__symbolic":"reference","name":"ɵbb"},{"__symbolic":"reference","name":"ɵbc"},{"__symbolic":"reference","name":"ɵbd"},{"__symbolic":"reference","name":"ɵbe"},{"__symbolic":"reference","name":"ɵbf"},{"__symbolic":"reference","name":"ɵbg"},{"__symbolic":"reference","name":"ɵbh"},{"__symbolic":"reference","name":"ɵbi"},{"__symbolic":"reference","name":"ɵbj"},{"__symbolic":"reference","name":"ɵbk"},{"__symbolic":"reference","name":"ɵbl"},{"__symbolic":"reference","name":"ɵbm"},{"__symbolic":"reference","name":"ɵbn"}],"exports":[{"__symbolic":"reference","module":"@angular/common","name":"CommonModule","line":70,"character":4},{"__symbolic":"reference","module":"@angular/common/http","name":"HttpClientModule","line":71,"character":4},{"__symbolic":"reference","module":"@angular/forms","name":"FormsModule","line":72,"character":4},{"__symbolic":"reference","module":"@angular/forms","name":"ReactiveFormsModule","line":73,"character":4},{"__symbolic":"reference","module":"@angular/router","name":"RouterModule","line":74,"character":4},{"__symbolic":"reference","name":"ɵz"},{"__symbolic":"reference","name":"ɵba"},{"__symbolic":"reference","name":"ɵbn"},{"__symbolic":"reference","name":"ɵy"},{"__symbolic":"reference","name":"ɵbb"},{"__symbolic":"reference","name":"ɵbc"},{"__symbolic":"reference","name":"ɵbd"},{"__symbolic":"reference","name":"ɵbe"},{"__symbolic":"reference","name":"ɵbh"},{"__symbolic":"reference","name":"ɵbi"},{"__symbolic":"reference","name":"ɵbj"},{"__symbolic":"reference","name":"ɵbk"},{"__symbolic":"reference","name":"ɵbm"},{"__symbolic":"reference","name":"ɵbl"},{"__symbolic":"reference","name":"ɵbf"},{"__symbolic":"reference","name":"ɵbg"},{"__symbolic":"reference","name":"ɵbf"}],"providers":[{"__symbolic":"reference","name":"ɵbf"}],"entryComponents":[{"__symbolic":"reference","name":"ɵz"},{"__symbolic":"reference","name":"ɵba"},{"__symbolic":"reference","name":"ɵy"}]}]}],"members":{},"statics":{"forRoot":{"__symbolic":"function","parameters":["options"],"defaults":[{}],"value":{"ngModule":{"__symbolic":"reference","name":"CoreModule"},"providers":[{"__symbolic":"reference","name":"ɵbp"},{"provide":{"__symbolic":"reference","module":"@ngxs/store","name":"NGXS_PLUGINS","line":107,"character":19},"useClass":{"__symbolic":"reference","name":"ɵbr"},"multi":true},{"provide":{"__symbolic":"reference","name":"ɵbq"},"useValue":{"__symbolic":"reference","name":"options"}},{"provide":{"__symbolic":"reference","module":"@angular/common/http","name":"HTTP_INTERCEPTORS","line":116,"character":19},"useClass":{"__symbolic":"reference","name":"ɵbs"},"multi":true},{"provide":{"__symbolic":"reference","module":"@angular/core","name":"APP_INITIALIZER","line":121,"character":19},"multi":true,"deps":[{"__symbolic":"reference","module":"@angular/core","name":"Injector","line":123,"character":17}],"useFactory":{"__symbolic":"reference","name":"ɵbt"}},{"provide":{"__symbolic":"reference","module":"@angular/core","name":"APP_INITIALIZER","line":127,"character":19},"multi":true,"deps":[{"__symbolic":"reference","module":"@angular/core","name":"Injector","line":129,"character":17}],"useFactory":{"__symbolic":"reference","name":"ɵbu"}},{"__symbolic":"spread","expression":{"__symbolic":"select","expression":{"__symbolic":"call","expression":{"__symbolic":"select","expression":{"__symbolic":"reference","module":"angular-oauth2-oidc","name":"OAuthModule","line":132,"character":11},"member":"forRoot"}},"member":"providers"}},{"provide":{"__symbolic":"reference","module":"angular-oauth2-oidc","name":"OAuthStorage","line":133,"character":19},"useFactory":{"__symbolic":"reference","name":"storageFactory"}}]}}}},"ɵa":{"__symbolic":"class","decorators":[{"__symbolic":"call","expression":{"__symbolic":"reference","module":"@ngxs/store","name":"State","line":6,"character":1},"arguments":[{"name":"ReplaceableComponentsState","defaults":{"replaceableComponents":[]}}]},{"__symbolic":"call","expression":{"__symbolic":"reference","module":"@angular/core","name":"Injectable","line":10,"character":1}}],"members":{"replaceableComponentsAction":[{"__symbolic":"method","decorators":[{"__symbolic":"call","expression":{"__symbolic":"reference","module":"@ngxs/store","name":"Action","line":30,"character":3},"arguments":[{"__symbolic":"reference","name":"ɵb"}]}]}]},"statics":{"getAll":{"__symbolic":"function","parameters":["replaceableComponents"],"value":{"__symbolic":"binop","operator":"||","left":{"__symbolic":"reference","name":"replaceableComponents"},"right":[]}}}},"ɵb":{"__symbolic":"class","members":{"__ctor__":[{"__symbolic":"constructor","parameters":[{"__symbolic":"select","expression":{"__symbolic":"reference","name":"ɵc"},"member":"ReplaceableComponent"}]}]},"statics":{"type":"[ReplaceableComponents] Add"}},"ɵd":{"__symbolic":"class","decorators":[{"__symbolic":"call","expression":{"__symbolic":"reference","module":"@ngxs/store","name":"State","line":7,"character":1},"arguments":[{"name":"ProfileState","defaults":{}}]},{"__symbolic":"call","expression":{"__symbolic":"reference","module":"@angular/core","name":"Injectable","line":11,"character":1}}],"members":{"__ctor__":[{"__symbolic":"constructor","parameters":[{"__symbolic":"reference","name":"ɵe"}]}],"getProfile":[{"__symbolic":"method","decorators":[{"__symbolic":"call","expression":{"__symbolic":"reference","module":"@ngxs/store","name":"Action","line":20,"character":3},"arguments":[{"__symbolic":"reference","name":"ɵg"}]}]}],"updateProfile":[{"__symbolic":"method","decorators":[{"__symbolic":"call","expression":{"__symbolic":"reference","module":"@ngxs/store","name":"Action","line":31,"character":3},"arguments":[{"__symbolic":"reference","name":"ɵh"}]}]}],"changePassword":[{"__symbolic":"method","decorators":[{"__symbolic":"call","expression":{"__symbolic":"reference","module":"@ngxs/store","name":"Action","line":42,"character":3},"arguments":[{"__symbolic":"reference","name":"ɵi"}]}]}]},"statics":{"getProfile":{"__symbolic":"function","parameters":["profile"],"value":{"__symbolic":"reference","name":"profile"}}}},"ɵe":{"__symbolic":"class","decorators":[{"__symbolic":"call","expression":{"__symbolic":"reference","module":"@angular/core","name":"Injectable","line":5,"character":1},"arguments":[{"providedIn":"root"}]}],"members":{"__ctor__":[{"__symbolic":"constructor","parameters":[{"__symbolic":"reference","name":"ɵf"}]}],"get":[{"__symbolic":"method"}],"update":[{"__symbolic":"method"}],"changePassword":[{"__symbolic":"method"}]},"statics":{"ngInjectableDef":{}}},"ɵf":{"__symbolic":"class","decorators":[{"__symbolic":"call","expression":{"__symbolic":"reference","module":"@angular/core","name":"Injectable","line":9,"character":1},"arguments":[{"providedIn":"root"}]}],"members":{"__ctor__":[{"__symbolic":"constructor","parameters":[{"__symbolic":"reference","module":"@angular/common/http","name":"HttpClient","line":13,"character":28},{"__symbolic":"reference","module":"@ngxs/store","name":"Store","line":13,"character":55}]}],"handleError":[{"__symbolic":"method"}],"request":[{"__symbolic":"method"}]},"statics":{"ngInjectableDef":{}}},"ɵg":{"__symbolic":"class","members":{},"statics":{"type":"[Profile] Get"}},"ɵh":{"__symbolic":"class","members":{"__ctor__":[{"__symbolic":"constructor","parameters":[{"__symbolic":"select","expression":{"__symbolic":"reference","name":"ɵj"},"member":"Response"}]}]},"statics":{"type":"[Profile] Update"}},"ɵi":{"__symbolic":"class","members":{"__ctor__":[{"__symbolic":"constructor","parameters":[{"__symbolic":"select","expression":{"__symbolic":"reference","name":"ɵj"},"member":"ChangePasswordRequest"}]}]},"statics":{"type":"[Profile] Change Password"}},"ɵk":{"__symbolic":"class","decorators":[{"__symbolic":"call","expression":{"__symbolic":"reference","module":"@ngxs/store","name":"State","line":24,"character":1},"arguments":[{"name":"SessionState","defaults":{"sessionDetail":{"openedTabCount":0}}}]},{"__symbolic":"call","expression":{"__symbolic":"reference","module":"@angular/core","name":"Injectable","line":28,"character":1}}],"members":{"__ctor__":[{"__symbolic":"constructor","parameters":[{"__symbolic":"reference","name":"ɵl"},{"__symbolic":"reference","module":"angular-oauth2-oidc","name":"OAuthService","line":47,"character":26},{"__symbolic":"reference","module":"@ngxs/store","name":"Store","line":48,"character":19},{"__symbolic":"reference","module":"@ngxs/store","name":"Actions","line":49,"character":21}]}],"setLanguage":[{"__symbolic":"method","decorators":[{"__symbolic":"call","expression":{"__symbolic":"reference","module":"@ngxs/store","name":"Action","line":77,"character":3},"arguments":[{"__symbolic":"reference","name":"ɵm"}]}]}],"setTenant":[{"__symbolic":"method","decorators":[{"__symbolic":"call","expression":{"__symbolic":"reference","module":"@ngxs/store","name":"Action","line":88,"character":3},"arguments":[{"__symbolic":"reference","name":"ɵn"}]}]}],"setRemember":[{"__symbolic":"method","decorators":[{"__symbolic":"call","expression":{"__symbolic":"reference","module":"@ngxs/store","name":"Action","line":95,"character":3},"arguments":[{"__symbolic":"reference","name":"ɵp"}]}]}],"modifyOpenedTabCount":[{"__symbolic":"method","decorators":[{"__symbolic":"call","expression":{"__symbolic":"reference","module":"@ngxs/store","name":"Action","line":110,"character":3},"arguments":[{"__symbolic":"reference","name":"ɵo"}]}]}]},"statics":{"getLanguage":{"__symbolic":"function","parameters":["language"],"value":{"__symbolic":"reference","name":"language"}},"getTenant":{"__symbolic":"function","parameters":["tenant"],"value":{"__symbolic":"reference","name":"tenant"}},"getSessionDetail":{"__symbolic":"function","parameters":["sessionDetail"],"value":{"__symbolic":"reference","name":"sessionDetail"}}}},"ɵl":{"__symbolic":"class","decorators":[{"__symbolic":"call","expression":{"__symbolic":"reference","module":"@angular/core","name":"Injectable","line":10,"character":1},"arguments":[{"providedIn":"root"}]}],"members":{"__ctor__":[{"__symbolic":"constructor","parameterDecorators":[null,null,null,[{"__symbolic":"call","expression":{"__symbolic":"reference","module":"@angular/core","name":"Optional","line":23,"character":5}},{"__symbolic":"call","expression":{"__symbolic":"reference","module":"@angular/core","name":"SkipSelf","line":24,"character":5}}]],"parameters":[{"__symbolic":"reference","module":"@ngxs/store","name":"Store","line":20,"character":19},{"__symbolic":"reference","module":"@angular/router","name":"Router","line":21,"character":20},{"__symbolic":"reference","module":"@angular/core","name":"NgZone","line":22,"character":20},{"__symbolic":"reference","name":"ɵl"}]}],"setRouteReuse":[{"__symbolic":"method"}],"registerLocale":[{"__symbolic":"method"}],"get":[{"__symbolic":"method"}],"instant":[{"__symbolic":"method"}]},"statics":{"ngInjectableDef":{}}},"ɵm":{"__symbolic":"class","members":{"__ctor__":[{"__symbolic":"constructor","parameters":[{"__symbolic":"reference","name":"string"}]}]},"statics":{"type":"[Session] Set Language"}},"ɵn":{"__symbolic":"class","members":{"__ctor__":[{"__symbolic":"constructor","parameters":[{"__symbolic":"select","expression":{"__symbolic":"reference","name":"ɵq"},"member":"BasicItem"}]}]},"statics":{"type":"[Session] Set Tenant"}},"ɵo":{"__symbolic":"class","members":{"__ctor__":[{"__symbolic":"constructor","parameters":[{"__symbolic":"error","message":"Expression form not supported","line":12,"character":32,"module":"./lib/actions/session.actions"}]}]},"statics":{"type":"[Session] Modify Opened Tab Count"}},"ɵp":{"__symbolic":"class","members":{"__ctor__":[{"__symbolic":"constructor","parameters":[{"__symbolic":"reference","name":"boolean"}]}]},"statics":{"type":"[Session] Set Remember"}},"ɵr":{"__symbolic":"class","decorators":[{"__symbolic":"call","expression":{"__symbolic":"reference","module":"@ngxs/store","name":"State","line":18,"character":1},"arguments":[{"name":"ConfigState","defaults":{}}]},{"__symbolic":"call","expression":{"__symbolic":"reference","module":"@angular/core","name":"Injectable","line":22,"character":1}}],"members":{"__ctor__":[{"__symbolic":"constructor","parameters":[{"__symbolic":"reference","name":"ɵs"},{"__symbolic":"reference","module":"@ngxs/store","name":"Store","line":199,"character":19}]}],"addData":[{"__symbolic":"method","decorators":[{"__symbolic":"call","expression":{"__symbolic":"reference","module":"@ngxs/store","name":"Action","line":202,"character":3},"arguments":[{"__symbolic":"reference","name":"ɵu"}]}]}],"patchRoute":[{"__symbolic":"method","decorators":[{"__symbolic":"call","expression":{"__symbolic":"reference","module":"@ngxs/store","name":"Action","line":224,"character":3},"arguments":[{"__symbolic":"reference","name":"ɵt"}]}]}],"addRoute":[{"__symbolic":"method","decorators":[{"__symbolic":"call","expression":{"__symbolic":"reference","module":"@ngxs/store","name":"Action","line":246,"character":3},"arguments":[{"__symbolic":"reference","name":"ɵv"}]}]}],"setEnvironment":[{"__symbolic":"method","decorators":[{"__symbolic":"call","expression":{"__symbolic":"reference","module":"@ngxs/store","name":"Action","line":301,"character":3},"arguments":[{"__symbolic":"reference","name":"ɵw"}]}]}]},"statics":{"getAll":{"__symbolic":"function","parameters":["state"],"value":{"__symbolic":"reference","name":"state"}},"getApplicationInfo":{"__symbolic":"function","parameters":["state"],"value":{"__symbolic":"binop","operator":"||","left":{"__symbolic":"select","expression":{"__symbolic":"select","expression":{"__symbolic":"reference","name":"state"},"member":"environment"},"member":"application"},"right":{}}}}},"ɵs":{"__symbolic":"class","decorators":[{"__symbolic":"call","expression":{"__symbolic":"reference","module":"@angular/core","name":"Injectable","line":6,"character":1},"arguments":[{"providedIn":"root"}]}],"members":{"__ctor__":[{"__symbolic":"constructor","parameters":[{"__symbolic":"reference","name":"ɵf"}]}],"getConfiguration":[{"__symbolic":"method"}]},"statics":{"ngInjectableDef":{}}},"ɵt":{"__symbolic":"class","members":{"__ctor__":[{"__symbolic":"constructor","parameters":[{"__symbolic":"reference","name":"string"},{"__symbolic":"error","message":"Could not resolve type","line":5,"character":52,"context":{"typeName":"Partial"},"module":"./lib/actions/config.actions"}]}]},"statics":{"type":"[Config] Patch Route By Name"}},"ɵu":{"__symbolic":"class","members":{},"statics":{"type":"[Config] Get App Configuration"}},"ɵv":{"__symbolic":"class","members":{"__ctor__":[{"__symbolic":"constructor","parameters":[{"__symbolic":"error","message":"Could not resolve type","line":17,"character":30,"context":{"typeName":"Omit"},"module":"./lib/actions/config.actions"}]}]},"statics":{"type":"[Config] Add Route"}},"ɵw":{"__symbolic":"class","members":{"__ctor__":[{"__symbolic":"constructor","parameters":[{"__symbolic":"select","expression":{"__symbolic":"reference","name":"ɵx"},"member":"Environment"}]}]},"statics":{"type":"[Config] Set Environment"}},"ɵy":{"__symbolic":"class","decorators":[{"__symbolic":"call","expression":{"__symbolic":"reference","module":"@angular/core","name":"Component","line":9,"character":1},"arguments":[{"selector":"abp-replaceable-route-container","template":"\n    <ng-container *ngComponentOutlet=\"externalComponent || defaultComponent\"></ng-container>\n  "}]}],"members":{"__ctor__":[{"__symbolic":"constructor","parameters":[{"__symbolic":"reference","module":"@angular/router","name":"ActivatedRoute","line":22,"character":29},{"__symbolic":"reference","module":"@ngxs/store","name":"Store","line":22,"character":60}]}],"ngOnInit":[{"__symbolic":"method"}],"ngOnDestroy":[{"__symbolic":"method"}]}},"ɵz":{"__symbolic":"class","decorators":[{"__symbolic":"call","expression":{"__symbolic":"reference","module":"@angular/core","name":"Component","line":2,"character":1},"arguments":[{"selector":"abp-router-outlet","template":"\n    <router-outlet></router-outlet>\n  "}]}],"members":{}},"ɵba":{"__symbolic":"class","decorators":[{"__symbolic":"call","expression":{"__symbolic":"reference","module":"@angular/core","name":"Component","line":11,"character":1},"arguments":[{"selector":"abp-dynamic-layout","template":"\n    <ng-container *ngTemplateOutlet=\"layout ? componentOutlet : routerOutlet\"></ng-container>\n    <ng-template #routerOutlet><router-outlet></router-outlet></ng-template>\n    <ng-template #componentOutlet\n      ><ng-container *ngComponentOutlet=\"layout\"></ng-container\n    ></ng-template>\n  "}]}],"members":{"requirements$":[{"__symbolic":"property","decorators":[{"__symbolic":"call","expression":{"__symbolic":"reference","module":"@ngxs/store","name":"Select","line":22,"character":3},"arguments":[{"__symbolic":"call","expression":{"__symbolic":"select","expression":{"__symbolic":"reference","name":"ɵr"},"member":"getOne"},"arguments":["requirements"]}]}]}],"__ctor__":[{"__symbolic":"constructor","parameters":[{"__symbolic":"reference","module":"@angular/router","name":"Router","line":26,"character":30},{"__symbolic":"reference","module":"@angular/router","name":"ActivatedRoute","line":26,"character":53},{"__symbolic":"reference","module":"@ngxs/store","name":"Store","line":26,"character":84}]}],"ngOnDestroy":[{"__symbolic":"method"}]}},"ɵbb":{"__symbolic":"class","decorators":[{"__symbolic":"call","expression":{"__symbolic":"reference","module":"@angular/core","name":"Directive","line":2,"character":1},"arguments":[{"selector":"[autofocus]"}]}],"members":{"delay":[{"__symbolic":"property","decorators":[{"__symbolic":"call","expression":{"__symbolic":"reference","module":"@angular/core","name":"Input","line":7,"character":3},"arguments":["autofocus"]}]}],"__ctor__":[{"__symbolic":"constructor","parameters":[{"__symbolic":"reference","module":"@angular/core","name":"ElementRef","line":10,"character":29}]}],"ngAfterViewInit":[{"__symbolic":"method"}]}},"ɵbc":{"__symbolic":"class","decorators":[{"__symbolic":"call","expression":{"__symbolic":"reference","module":"@angular/core","name":"Directive","line":2,"character":1},"arguments":[{"selector":"[abpEllipsis]"}]}],"members":{"width":[{"__symbolic":"property","decorators":[{"__symbolic":"call","expression":{"__symbolic":"reference","module":"@angular/core","name":"Input","line":6,"character":3},"arguments":["abpEllipsis"]}]}],"title":[{"__symbolic":"property","decorators":[{"__symbolic":"call","expression":{"__symbolic":"reference","module":"@angular/core","name":"HostBinding","line":9,"character":3},"arguments":["title"]},{"__symbolic":"call","expression":{"__symbolic":"reference","module":"@angular/core","name":"Input","line":10,"character":3}}]}],"enabled":[{"__symbolic":"property","decorators":[{"__symbolic":"call","expression":{"__symbolic":"reference","module":"@angular/core","name":"Input","line":13,"character":3},"arguments":["abpEllipsisEnabled"]}]}],"inlineClass":[{"__symbolic":"property","decorators":[{"__symbolic":"call","expression":{"__symbolic":"reference","module":"@angular/core","name":"HostBinding","line":16,"character":3},"arguments":["class.abp-ellipsis-inline"]}]}],"class":[{"__symbolic":"property","decorators":[{"__symbolic":"call","expression":{"__symbolic":"reference","module":"@angular/core","name":"HostBinding","line":21,"character":3},"arguments":["class.abp-ellipsis"]}]}],"maxWidth":[{"__symbolic":"property","decorators":[{"__symbolic":"call","expression":{"__symbolic":"reference","module":"@angular/core","name":"HostBinding","line":26,"character":3},"arguments":["style.max-width"]}]}],"__ctor__":[{"__symbolic":"constructor","parameters":[{"__symbolic":"reference","module":"@angular/core","name":"ChangeDetectorRef","line":31,"character":29},{"__symbolic":"reference","module":"@angular/core","name":"ElementRef","line":31,"character":63}]}],"ngAfterViewInit":[{"__symbolic":"method"}]}},"ɵbd":{"__symbolic":"class","decorators":[{"__symbolic":"call","expression":{"__symbolic":"reference","module":"@angular/core","name":"Directive","line":26,"character":1},"arguments":[{"selector":"[abpFor]"}]}],"members":{"items":[{"__symbolic":"property","decorators":[{"__symbolic":"call","expression":{"__symbolic":"reference","module":"@angular/core","name":"Input","line":30,"character":3},"arguments":["abpForOf"]}]}],"orderBy":[{"__symbolic":"property","decorators":[{"__symbolic":"call","expression":{"__symbolic":"reference","module":"@angular/core","name":"Input","line":33,"character":3},"arguments":["abpForOrderBy"]}]}],"orderDir":[{"__symbolic":"property","decorators":[{"__symbolic":"call","expression":{"__symbolic":"reference","module":"@angular/core","name":"Input","line":36,"character":3},"arguments":["abpForOrderDir"]}]}],"filterBy":[{"__symbolic":"property","decorators":[{"__symbolic":"call","expression":{"__symbolic":"reference","module":"@angular/core","name":"Input","line":39,"character":3},"arguments":["abpForFilterBy"]}]}],"filterVal":[{"__symbolic":"property","decorators":[{"__symbolic":"call","expression":{"__symbolic":"reference","module":"@angular/core","name":"Input","line":42,"character":3},"arguments":["abpForFilterVal"]}]}],"trackBy":[{"__symbolic":"property","decorators":[{"__symbolic":"call","expression":{"__symbolic":"reference","module":"@angular/core","name":"Input","line":45,"character":3},"arguments":["abpForTrackBy"]}]}],"compareBy":[{"__symbolic":"property","decorators":[{"__symbolic":"call","expression":{"__symbolic":"reference","module":"@angular/core","name":"Input","line":48,"character":3},"arguments":["abpForCompareBy"]}]}],"emptyRef":[{"__symbolic":"property","decorators":[{"__symbolic":"call","expression":{"__symbolic":"reference","module":"@angular/core","name":"Input","line":51,"character":3},"arguments":["abpForEmptyRef"]}]}],"__ctor__":[{"__symbolic":"constructor","parameters":[{"__symbolic":"reference","name":"TemplateRef","module":"@angular/core","arguments":[{"__symbolic":"error","message":"Reference to non-exported class","line":18,"character":0,"context":{"className":"AbpForContext"},"module":"./lib/directives/for.directive"}]},{"__symbolic":"reference","module":"@angular/core","name":"ViewContainerRef","line":68,"character":19},{"__symbolic":"reference","module":"@angular/core","name":"IterableDiffers","line":69,"character":21}]}],"iterateOverAppliedOperations":[{"__symbolic":"method"}],"iterateOverAttachedViews":[{"__symbolic":"method"}],"projectItems":[{"__symbolic":"method"}],"sortItems":[{"__symbolic":"method"}],"ngOnChanges":[{"__symbolic":"method"}]}},"ɵbe":{"__symbolic":"class","decorators":[{"__symbolic":"call","expression":{"__symbolic":"reference","module":"@angular/core","name":"Directive","line":18,"character":1},"arguments":[{"selector":"form[ngSubmit][formGroup]"}]}],"members":{"debounce":[{"__symbolic":"property","decorators":[{"__symbolic":"call","expression":{"__symbolic":"reference","module":"@angular/core","name":"Input","line":23,"character":3}}]}],"notValidateOnSubmit":[{"__symbolic":"property","decorators":[{"__symbolic":"call","expression":{"__symbolic":"reference","module":"@angular/core","name":"Input","line":26,"character":3}}]}],"ngSubmit":[{"__symbolic":"property","decorators":[{"__symbolic":"call","expression":{"__symbolic":"reference","module":"@angular/core","name":"Output","line":29,"character":3}}]}],"__ctor__":[{"__symbolic":"constructor","parameterDecorators":[[{"__symbolic":"call","expression":{"__symbolic":"reference","module":"@angular/core","name":"Self","line":34,"character":5}}],null,null],"parameters":[{"__symbolic":"reference","module":"@angular/forms","name":"FormGroupDirective","line":34,"character":40},{"__symbolic":"reference","name":"ElementRef","module":"@angular/core","arguments":[{"__symbolic":"error","message":"Could not resolve type","line":35,"character":29,"context":{"typeName":"HTMLFormElement"},"module":"./lib/directives/form-submit.directive"}]},{"__symbolic":"reference","module":"@angular/core","name":"ChangeDetectorRef","line":36,"character":19}]}],"ngOnInit":[{"__symbolic":"method"}],"ngOnDestroy":[{"__symbolic":"method"}],"markAsDirty":[{"__symbolic":"method"}]}},"ɵbf":{"__symbolic":"class","decorators":[{"__symbolic":"call","expression":{"__symbolic":"reference","module":"@angular/core","name":"Injectable","line":5,"character":1}},{"__symbolic":"call","expression":{"__symbolic":"reference","module":"@angular/core","name":"Pipe","line":6,"character":1},"arguments":[{"name":"abpLocalization"}]}],"members":{"__ctor__":[{"__symbolic":"constructor","parameters":[{"__symbolic":"reference","module":"@ngxs/store","name":"Store","line":10,"character":29}]}],"transform":[{"__symbolic":"method"}]}},"ɵbg":{"__symbolic":"class","decorators":[{"__symbolic":"call","expression":{"__symbolic":"reference","module":"@angular/core","name":"Injectable","line":2,"character":1}},{"__symbolic":"call","expression":{"__symbolic":"reference","module":"@angular/core","name":"Pipe","line":3,"character":1},"arguments":[{"name":"abpSort"}]}],"members":{"transform":[{"__symbolic":"method"}]}},"ɵbh":{"__symbolic":"class","decorators":[{"__symbolic":"call","expression":{"__symbolic":"reference","module":"@angular/core","name":"Directive","line":2,"character":1},"arguments":[{"selector":"[abpInit]"}]}],"members":{"init":[{"__symbolic":"property","decorators":[{"__symbolic":"call","expression":{"__symbolic":"reference","module":"@angular/core","name":"Output","line":4,"character":3},"arguments":["abpInit"]}]}],"__ctor__":[{"__symbolic":"constructor","parameters":[{"__symbolic":"reference","module":"@angular/core","name":"ElementRef","line":6,"character":29}]}],"ngAfterViewInit":[{"__symbolic":"method"}]}},"ɵbi":{"__symbolic":"class","decorators":[{"__symbolic":"call","expression":{"__symbolic":"reference","module":"@angular/core","name":"Directive","line":18,"character":1},"arguments":[{"selector":"[abpPermission]"}]}],"members":{"condition":[{"__symbolic":"property","decorators":[{"__symbolic":"call","expression":{"__symbolic":"reference","module":"@angular/core","name":"Input","line":22,"character":3},"arguments":["abpPermission"]}]}],"__ctor__":[{"__symbolic":"constructor","parameterDecorators":[null,null,null,[{"__symbolic":"call","expression":{"__symbolic":"reference","module":"@angular/core","name":"Optional","line":30,"character":5}}],null],"parameters":[{"__symbolic":"reference","module":"@angular/core","name":"ElementRef","line":27,"character":19},{"__symbolic":"reference","module":"@angular/core","name":"Renderer2","line":28,"character":22},{"__symbolic":"reference","module":"@ngxs/store","name":"Store","line":29,"character":19},{"__symbolic":"reference","name":"TemplateRef","module":"@angular/core","arguments":[{"__symbolic":"reference","name":"any"}]},{"__symbolic":"reference","module":"@angular/core","name":"ViewContainerRef","line":31,"character":19}]}],"check":[{"__symbolic":"method"}],"ngOnInit":[{"__symbolic":"method"}],"ngOnDestroy":[{"__symbolic":"method"}],"ngOnChanges":[{"__symbolic":"method"}]}},"ɵbj":{"__symbolic":"class","decorators":[{"__symbolic":"call","expression":{"__symbolic":"reference","module":"@angular/core","name":"Directive","line":4,"character":1},"arguments":[{"selector":"[abpVisibility]"}]}],"members":{"focusedElement":[{"__symbolic":"property","decorators":[{"__symbolic":"call","expression":{"__symbolic":"reference","module":"@angular/core","name":"Input","line":8,"character":3},"arguments":["abpVisibility"]}]}],"__ctor__":[{"__symbolic":"constructor","parameterDecorators":[[{"__symbolic":"call","expression":{"__symbolic":"reference","module":"@angular/core","name":"Optional","line":13,"character":15}}],null],"parameters":[{"__symbolic":"reference","module":"@angular/core","name":"ElementRef","line":13,"character":41},{"__symbolic":"reference","module":"@angular/core","name":"Renderer2","line":13,"character":71}]}],"ngAfterViewInit":[{"__symbolic":"method"}],"disconnect":[{"__symbolic":"method"}],"removeFromDOM":[{"__symbolic":"method"}]}},"ɵbk":{"__symbolic":"class","decorators":[{"__symbolic":"call","expression":{"__symbolic":"reference","module":"@angular/core","name":"Directive","line":13,"character":1},"arguments":[{"selector":"[input.debounce]"}]}],"members":{"debounce":[{"__symbolic":"property","decorators":[{"__symbolic":"call","expression":{"__symbolic":"reference","module":"@angular/core","name":"Input","line":18,"character":3}}]}],"debounceEvent":[{"__symbolic":"property","decorators":[{"__symbolic":"call","expression":{"__symbolic":"reference","module":"@angular/core","name":"Output","line":20,"character":3},"arguments":["input.debounce"]}]}],"__ctor__":[{"__symbolic":"constructor","parameters":[{"__symbolic":"reference","module":"@angular/core","name":"ElementRef","line":22,"character":26}]}],"ngOnInit":[{"__symbolic":"method"}],"ngOnDestroy":[{"__symbolic":"method"}]}},"ɵbl":{"__symbolic":"class","decorators":[{"__symbolic":"call","expression":{"__symbolic":"reference","module":"@angular/core","name":"Directive","line":4,"character":1},"arguments":[{"selector":"[click.stop]"}]}],"members":{"stopPropEvent":[{"__symbolic":"property","decorators":[{"__symbolic":"call","expression":{"__symbolic":"reference","module":"@angular/core","name":"Output","line":9,"character":3},"arguments":["click.stop"]}]}],"__ctor__":[{"__symbolic":"constructor","parameters":[{"__symbolic":"reference","module":"@angular/core","name":"ElementRef","line":11,"character":26}]}],"ngOnInit":[{"__symbolic":"method"}],"ngOnDestroy":[{"__symbolic":"method"}]}},"ɵbm":{"__symbolic":"class","decorators":[{"__symbolic":"call","expression":{"__symbolic":"reference","module":"@angular/core","name":"Directive","line":23,"character":1},"arguments":[{"selector":"[abpReplaceableTemplate]"}]}],"members":{"data":[{"__symbolic":"property","decorators":[{"__symbolic":"call","expression":{"__symbolic":"reference","module":"@angular/core","name":"Input","line":25,"character":3},"arguments":["abpReplaceableTemplate"]}]}],"__ctor__":[{"__symbolic":"constructor","parameters":[{"__symbolic":"reference","module":"@angular/core","name":"Injector","line":44,"character":22},{"__symbolic":"reference","name":"TemplateRef","module":"@angular/core","arguments":[{"__symbolic":"reference","name":"any"}]},{"__symbolic":"reference","module":"@angular/core","name":"ComponentFactoryResolver","line":46,"character":19},{"__symbolic":"reference","module":"@angular/core","name":"ViewContainerRef","line":47,"character":19},{"__symbolic":"reference","module":"@ngxs/store","name":"Store","line":48,"character":19}]}],"ngOnInit":[{"__symbolic":"method"}],"ngOnChanges":[{"__symbolic":"method"}],"ngOnDestroy":[{"__symbolic":"method"}],"setDefaultComponentInputs":[{"__symbolic":"method"}],"setProvidedData":[{"__symbolic":"method"}],"resetDefaultComponent":[{"__symbolic":"method"}]}},"ɵbn":{"__symbolic":"class","arity":2,"decorators":[{"__symbolic":"call","expression":{"__symbolic":"reference","module":"@angular/core","name":"Component","line":5,"character":1},"arguments":[{"template":""}]}],"members":{"disabled":[{"__symbolic":"property","decorators":[{"__symbolic":"call","expression":{"__symbolic":"reference","module":"@angular/core","name":"Input","line":12,"character":3}}]}],"readonly":[{"__symbolic":"property","decorators":[{"__symbolic":"call","expression":{"__symbolic":"reference","module":"@angular/core","name":"Input","line":15,"character":3}}]}],"valueFn":[{"__symbolic":"property","decorators":[{"__symbolic":"call","expression":{"__symbolic":"reference","module":"@angular/core","name":"Input","line":18,"character":3}}]}],"valueLimitFn":[{"__symbolic":"property","decorators":[{"__symbolic":"call","expression":{"__symbolic":"reference","module":"@angular/core","name":"Input","line":21,"character":3}}]}],"value":[{"__symbolic":"property","decorators":[{"__symbolic":"call","expression":{"__symbolic":"reference","module":"@angular/core","name":"Input","line":24,"character":3}}]}],"__ctor__":[{"__symbolic":"constructor","parameters":[{"__symbolic":"reference","module":"@angular/core","name":"Injector","line":42,"character":31}]}],"notifyValueChange":[{"__symbolic":"method"}],"writeValue":[{"__symbolic":"method"}],"registerOnChange":[{"__symbolic":"method"}],"registerOnTouched":[{"__symbolic":"method"}],"setDisabledState":[{"__symbolic":"method"}]}},"ɵbo":{"__symbolic":"class","extends":{"__symbolic":"reference","name":"String"},"members":{"__ctor__":[{"__symbolic":"constructor","parameters":[{"__symbolic":"reference","name":"ɵl"}]}],"toString":[{"__symbolic":"method"}],"valueOf":[{"__symbolic":"method"}]}},"ɵbp":{"provide":{"__symbolic":"reference","module":"@angular/core","name":"LOCALE_ID","line":20,"character":11},"useClass":{"__symbolic":"reference","name":"ɵbo"},"deps":[{"__symbolic":"reference","name":"ɵl"}]},"ɵbq":{"__symbolic":"new","expression":{"__symbolic":"reference","module":"@angular/core","name":"InjectionToken","line":15,"character":46},"arguments":["NGXS_CONFIG_PLUGIN_OPTIONS"]},"ɵbr":{"__symbolic":"class","decorators":[{"__symbolic":"call","expression":{"__symbolic":"reference","module":"@angular/core","name":"Injectable","line":17,"character":1}}],"members":{"__ctor__":[{"__symbolic":"constructor","parameterDecorators":[[{"__symbolic":"call","expression":{"__symbolic":"reference","module":"@angular/core","name":"Inject","line":22,"character":5},"arguments":[{"__symbolic":"reference","name":"ɵbq"}]}],null],"parameters":[{"__symbolic":"select","expression":{"__symbolic":"reference","name":"ɵq"},"member":"Root"},{"__symbolic":"reference","module":"@angular/router","name":"Router","line":23,"character":20}]}],"handle":[{"__symbolic":"method"}]}},"ɵbs":{"__symbolic":"class","decorators":[{"__symbolic":"call","expression":{"__symbolic":"reference","module":"@angular/core","name":"Injectable","line":8,"character":1}}],"members":{"__ctor__":[{"__symbolic":"constructor","parameters":[{"__symbolic":"reference","module":"angular-oauth2-oidc","name":"OAuthService","line":10,"character":36},{"__symbolic":"reference","module":"@ngxs/store","name":"Store","line":10,"character":65}]}],"intercept":[{"__symbolic":"method"}]}},"ɵbt":{"__symbolic":"function"},"ɵbu":{"__symbolic":"function"}},"origins":{"storageFactory":"./lib/core.module","CoreModule":"./lib/core.module","ɵa":"./lib/states/replaceable-components.state","ɵb":"./lib/actions/replaceable-components.actions","ɵc":"./lib/models/replaceable-components","ɵd":"./lib/states/profile.state","ɵe":"./lib/services/profile.service","ɵf":"./lib/services/rest.service","ɵg":"./lib/actions/profile.actions","ɵh":"./lib/actions/profile.actions","ɵi":"./lib/actions/profile.actions","ɵj":"./lib/models","ɵk":"./lib/states/session.state","ɵl":"./lib/services/localization.service","ɵm":"./lib/actions/session.actions","ɵn":"./lib/actions/session.actions","ɵo":"./lib/actions/session.actions","ɵp":"./lib/actions/session.actions","ɵq":"./lib/models","ɵr":"./lib/states/config.state","ɵs":"./lib/services/application-configuration.service","ɵt":"./lib/actions/config.actions","ɵu":"./lib/actions/config.actions","ɵv":"./lib/actions/config.actions","ɵw":"./lib/actions/config.actions","ɵx":"./lib/models/config","ɵy":"./lib/components/replaceable-route-container.component","ɵz":"./lib/components/router-outlet.component","ɵba":"./lib/components/dynamic-layout.component","ɵbb":"./lib/directives/autofocus.directive","ɵbc":"./lib/directives/ellipsis.directive","ɵbd":"./lib/directives/for.directive","ɵbe":"./lib/directives/form-submit.directive","ɵbf":"./lib/pipes/localization.pipe","ɵbg":"./lib/pipes/sort.pipe","ɵbh":"./lib/directives/init.directive","ɵbi":"./lib/directives/permission.directive","ɵbj":"./lib/directives/visibility.directive","ɵbk":"./lib/directives/debounce.directive","ɵbl":"./lib/directives/stop-propagation.directive","ɵbm":"./lib/directives/replaceable-template.directive","ɵbn":"./lib/abstracts/ng-model.component","ɵbo":"./lib/providers/locale.provider","ɵbp":"./lib/providers/locale.provider","ɵbq":"./lib/plugins/config.plugin","ɵbr":"./lib/plugins/config.plugin","ɵbs":"./lib/interceptors/api.interceptor","ɵbt":"./lib/utils/initial-utils","ɵbu":"./lib/utils/initial-utils"},"importAs":"@abp/ng.core"}